authzero.py
authzerolib-1.1.0.dist-info/LICENSE
authzerolib-1.1.0.dist-info/METADATA
authzerolib-1.1.0.dist-info/WHEEL
authzerolib-1.1.0.dist-info/top_level.txt
authzerolib-1.1.0.dist-info/RECORD
