Metadata-Version: 2.1
Name: authzerolib
Version: 1.1.0
Summary: A super simple and basic client lib for Auth0
Home-page: https://github.com/mozilla-iam/authzerolib
Author: Mozilla IAM
Author-email: gene@mozilla.com
License: MPL-2.0
Keywords: auth0 iam library
Platform: UNKNOWN
Classifier: Development Status :: 5 - Production/Stable
Classifier: Topic :: Software Development :: Libraries :: Python Modules
Classifier: License :: OSI Approved :: Mozilla Public License 2.0 (MPL 2.0)
License-File: LICENSE
Requires-Dist: requests
